cli_music_player_cthulhu-1.0.8.dist-info/licenses/LICENSE
musicplayer/__init__.py
musicplayer/config.py
musicplayer/engine.py
musicplayer/gui.py
musicplayer/launcher.py
musicplayer/main.py
musicplayer/mpris_stub.py
musicplayer/mpv_setup.py
musicplayer/search.py
musicplayer/utils.py
musicplayer/assets/frame1.png
musicplayer/assets/frame2.png
cli_music_player_cthulhu-1.0.8.dist-info/METADATA
cli_music_player_cthulhu-1.0.8.dist-info/WHEEL
cli_music_player_cthulhu-1.0.8.dist-info/entry_points.txt
cli_music_player_cthulhu-1.0.8.dist-info/top_level.txt
cli_music_player_cthulhu-1.0.8.dist-info/RECORD
