Metadata-Version: 2.4
Name: cli-music-player-cthulhu
Version: 1.0.8
Summary: A lightweight terminal music player with mpv engine and auto-setup
Author-email: Thiago Mendonça <tfariamendonca@gmail.com>
Classifier: Programming Language :: Python :: 3
Classifier: License :: OSI Approved :: GNU Affero General Public License v3
Classifier: Operating System :: POSIX :: Linux
Requires-Python: >=3.8
License-File: LICENSE
Requires-Dist: yt-dlp>=2023.0.0
Requires-Dist: windows-curses; sys_platform == "win32"
Requires-Dist: py7zr; sys_platform == "win32"
Requires-Dist: PyQt6>=6.4.0
Requires-Dist: mpris2; sys_platform == "linux"
Dynamic: license-file
